.DS_Store
didtool/__init__.py
didtool/cut.py
didtool/encoder.py
didtool/logger.py
didtool/metric.py
didtool/model.py
didtool/scorecard.py
didtool/selector.py
didtool/split.py
didtool/stats.py
didtool/transformer.py
didtool/utils.py
tests/__init__.py
tests/cut_test.py
tests/encoder_test.py
tests/metric_test.py
tests/model_test.py
tests/scorecard_test.py
tests/selector_test.py
tests/split_test.py
tests/stats_test.py
tests/transformer_test.py
didtool-0.1.3.dist-info/LICENSE
didtool-0.1.3.dist-info/METADATA
didtool-0.1.3.dist-info/WHEEL
didtool-0.1.3.dist-info/top_level.txt
didtool-0.1.3.dist-info/RECORD
