Metadata-Version: 2.1
Name: didtool
Version: 0.1.3
Summary: Tool set for feature engineering & modeling
Home-page: https://github.com/dustless/didtool
Author: dustless
Author-email: wuchenghui927@126.com
Classifier: Programming Language :: Python :: 3
Classifier: License :: OSI Approved :: MIT License
Classifier: Operating System :: OS Independent
Requires-Python: >=3.6
License-File: LICENSE
Requires-Dist: seaborn (>=0.10.1)
Requires-Dist: scikit-learn (>=0.24.1)
Requires-Dist: lightgbm (>=4.3.0)
Requires-Dist: sklearn2pmml (>=0.65.0)
Requires-Dist: bayesian-optimization (==1.2.0)
Requires-Dist: pandas (>=1.5.3)
Requires-Dist: numpy (>=1.20.3)
